pynetim/__init__.py
pynetim/cpp/__init__.py
pynetim/cpp/diffusion_model/__init__.py
pynetim/cpp/diffusion_model/diffusion_model.h
pynetim/cpp/diffusion_model/ic_bind.cpp
pynetim/cpp/diffusion_model/independent_cascade_model.cp38-win_amd64.pyd
pynetim/cpp/diffusion_model/independent_cascade_model.pyi
pynetim/cpp/diffusion_model/linear_threshold_model.cp38-win_amd64.pyd
pynetim/cpp/diffusion_model/linear_threshold_model.pyi
pynetim/cpp/diffusion_model/lt_bind.cpp
pynetim/cpp/graph/Graph.h
pynetim/cpp/graph/__init__.py
pynetim/cpp/graph/graph.cp38-win_amd64.pyd
pynetim/cpp/graph/graph.pyi
pynetim/cpp/graph/graph_bind.cpp
pynetim/py/__init__.py
pynetim/py/algorithms/RIS_algorithm.py
pynetim/py/algorithms/__init__.py
pynetim/py/algorithms/base_algorithm.py
pynetim/py/algorithms/heuristic_algorithm.py
pynetim/py/algorithms/simulation_algorithm.py
pynetim/py/decorator/__init__.py
pynetim/py/decorator/decorator.py
pynetim/py/diffusion_model/__init__.py
pynetim/py/diffusion_model/base_diffusion_model.py
pynetim/py/diffusion_model/independent_cascade_model.py
pynetim/py/diffusion_model/linear_threshold_model.py
pynetim/py/diffusion_model/run_monte_carlo_diffusion.py
pynetim/py/diffusion_model/susceptible_infected_model.py
pynetim/py/diffusion_model/susceptible_infected_recovered_model.py
pynetim/py/graph/__init__.py
pynetim/py/graph/graph.py
pynetim/utils/__init__.py
pynetim/utils/utils.py
pynetim-0.3.1.dist-info/LICENSE
pynetim-0.3.1.dist-info/METADATA
pynetim-0.3.1.dist-info/WHEEL
pynetim-0.3.1.dist-info/top_level.txt
pynetim-0.3.1.dist-info/RECORD
