Metadata-Version: 2.1
Name: pynetim
Version: 0.3.1
Summary: A Python library for Network Influence Maximization
Home-page: https://github.com/zzzkhj/PyNetIM
Author-email: Kaijing Zhang <zhkaij@foxmail.com>
License: MIT
Project-URL: Homepage, https://github.com/zzzkhj/PyNetIM
Project-URL: Repository, https://github.com/zzzkhj/PyNetIM
Project-URL: Issues, https://github.com/zzzkhj/PyNetIM/issues
Platform: UNKNOWN
Classifier: Programming Language :: Python :: 3
Classifier: License :: OSI Approved :: MIT License
Classifier: Operating System :: OS Independent
Requires-Python: >=3.8
License-File: LICENSE
Requires-Dist: networkx (>=2.6)
Requires-Dist: numpy (>=1.20)
